edge_mdt_tpc_nightly-1.2.0.20250929.15259.dist-info/licenses/LICENSE.md
edgemdt_tpc/__init__.py
edgemdt_tpc/get_tpc.py
edgemdt_tpc/version.py
edgemdt_tpc/data/__init__.py
edgemdt_tpc/data/imx500/__init__.py
edgemdt_tpc/data/imx500/tpc_v1_0.py
edgemdt_tpc/data/imx500/tpc_v1_0_lut.py
edgemdt_tpc/data/imx500/tpc_v4_0.py
edgemdt_tpc/data/imx500/tpc_v4_1.py
edgemdt_tpc/data/imx500/tpc_v5_0.py
edge_mdt_tpc_nightly-1.2.0.20250929.15259.dist-info/METADATA
edge_mdt_tpc_nightly-1.2.0.20250929.15259.dist-info/WHEEL
edge_mdt_tpc_nightly-1.2.0.20250929.15259.dist-info/top_level.txt
edge_mdt_tpc_nightly-1.2.0.20250929.15259.dist-info/RECORD
