Metadata-Version: 2.4
Name: edge-mdt-tpc-nightly
Version: 1.2.0.20250929.15259
Summary: EdgeMDT TPC package
Classifier: Programming Language :: Python :: 3
Classifier: License :: OSI Approved :: Apache Software License
Classifier: Operating System :: OS Independent
Classifier: Topic :: Scientific/Engineering :: Artificial Intelligence
License-File: LICENSE.md
Requires-Dist: model-compression-toolkit>=2.3
Dynamic: license-file
